eventum_content_manager/__init__.py
eventum_content_manager/manage.py
eventum_content_manager/py.typed
eventum_content_manager/tests/test_manage.py
eventum_content_manager/tests/test_validators.py
eventum_content_manager/validators.py
eventum_content_manager-1.1.0.dist-info/LICENSE
eventum_content_manager-1.1.0.dist-info/METADATA
eventum_content_manager-1.1.0.dist-info/WHEEL
eventum_content_manager-1.1.0.dist-info/RECORD
