Metadata-Version: 2.1
Name: eventum-content-manager
Version: 1.1.0
Summary: Content manager for Eventum
Home-page: https://github.com/Eventum-Generatives/EventumContentManager
License: Apache-2.0
Keywords: dependency
Author: Nikita Reznikov
Author-email: nikita.reznikov.public@mail.ru
Requires-Python: >=3.11,<4.0
Classifier: Development Status :: 5 - Production/Stable
Classifier: Intended Audience :: Developers
Classifier: License :: OSI Approved :: Apache Software License
Classifier: Operating System :: OS Independent
Classifier: Programming Language :: Python :: 3
Classifier: Programming Language :: Python :: 3.11
Classifier: Programming Language :: Python :: 3.12
Requires-Dist: pyyaml (>=6.0.1,<7.0.0)
Requires-Dist: types-pyyaml (>=6.0.12.20240311,<7.0.0.0)
Project-URL: Documentation, https://eventum-generatives.github.io/Website/
Project-URL: Repository, https://github.com/Eventum-Generatives/EventumContentManager
